ansible_waldur_module/__init__.py
ansible_waldur_module/waldur_batch_allocation.py
ansible_waldur_module/waldur_batch_offering.py
ansible_waldur_module/waldur_marketplace.py
ansible_waldur_module/waldur_marketplace_os_get_instance.py
ansible_waldur_module/waldur_marketplace_os_instance.py
ansible_waldur_module/waldur_marketplace_os_volume.py
ansible_waldur_module/waldur_os_floating_ip.py
ansible_waldur_module/waldur_os_instance_volume.py
ansible_waldur_module/waldur_os_security_group.py
ansible_waldur_module/waldur_os_security_group_gather_facts.py
ansible_waldur_module/waldur_os_snapshot.py
ansible_waldur_module/waldur_os_subnet.py
ansible_waldur_module/waldur_os_subnet_gather_facts.py
ansible_waldur_module-1.2.1.dist-info/LICENSE.md
ansible_waldur_module-1.2.1.dist-info/METADATA
ansible_waldur_module-1.2.1.dist-info/WHEEL
ansible_waldur_module-1.2.1.dist-info/RECORD
