Metadata-Version: 2.3
Name: ansible-waldur-module
Version: 1.2.1
Summary: Ansible module for the Waldur API.
License: MIT
Author: OpenNode Team
Author-email: info@opennodecloud.com
Requires-Python: >=3.8
Classifier: Intended Audience :: Developers
Classifier: Intended Audience :: System Administrators
Classifier: License :: OSI Approved :: MIT License
Classifier: Operating System :: OS Independent
Classifier: Programming Language :: Python :: 3
Classifier: Programming Language :: Python :: 3.8
Classifier: Programming Language :: Python :: 3.9
Classifier: Programming Language :: Python :: 3.10
Classifier: Programming Language :: Python :: 3.11
Classifier: Programming Language :: Python :: 3.12
Classifier: Programming Language :: Python :: 3.13
Requires-Dist: ansible-core (>=2.11.0)
Requires-Dist: pre-commit (>=2.13.0,<3.0.0)
Requires-Dist: python-waldur-client (>=0.6.2)
Requires-Dist: requests (>=2.6.0)
Requires-Dist: urllib3 (<2.0.0)
Project-URL: Homepage, https://waldur.com
